CHANGES.rst
LICENSE
README.rst
pyproject.toml
setup.cfg
setup.py
anacron/__init__.py
anacron/configuration.py
anacron/decorators.py
anacron/engine.py
anacron/schedule.py
anacron/sql_interface.py
anacron/utils.py
anacron/worker.py
anacron.egg-info/PKG-INFO
anacron.egg-info/SOURCES.txt
anacron.egg-info/dependency_links.txt
anacron.egg-info/top_level.txt
tests/test_engine.py
tests/test_schedule.py
tests/test_sql_interface.py
tests/test_worker.py